Warning: Binary file Test2 contains test.info.yangguo.zeus.common.bytecode.others.Test2
Compiled from "Test2.java"
public class test.info.yangguo.zeus.common.bytecode.others.Test2 {
  public test.info.yangguo.zeus.common.bytecode.others.Test2();
    Code:
       0: aload_0
       1: invokespecial #1                  // Method java/lang/Object."<init>":()V
       4: return

  public static void main(java.lang.String[]) throws java.lang.Exception;
    Code:
       0: new           #2                  // class test.info/yangguo/others/CountServiceImpl
       3: dup
       4: invokespecial #3                  // Method test.info/yangguo/others/CountServiceImpl."<init>":()V
       7: astore_1
       8: aload_1
       9: invokevirtual #4                  // Method java/lang/Object.getClass:()Ljava/lang/Class;
      12: ldc           #5                  // String count
      14: iconst_0
      15: anewarray     #6                  // class java/lang/Class
      18: invokevirtual #7                  // Method java/lang/Class.getMethod:(Ljava/lang/String;[Ljava/lang/Class;)Ljava/lang/reflect/Method;
      21: astore_2
      22: aload_2
      23: aload_1
      24: iconst_0
      25: anewarray     #8                  // class java/lang/Object
      28: invokevirtual #9                  // Method java/lang/reflect/Method.invoke:(Ljava/lang/Object;[Ljava/lang/Object;)Ljava/lang/Object;
      31: pop
      32: return
}